bareunpy/__init__.py
bareunpy/_corrector.py
bareunpy/_custom_dict.py
bareunpy/_custom_dict_client.py
bareunpy/_lang_service_client.py
bareunpy/_revision_service_client.py
bareunpy/_tagger.py
bareunpy/_tokenizer.py
bareunpy-1.7.2.dist-info/LICENSE
bareunpy-1.7.2.dist-info/METADATA
bareunpy-1.7.2.dist-info/WHEEL
bareunpy-1.7.2.dist-info/RECORD
